[
    {
      "state": "CHANDIGARH",
      "District": "CHANDIGARH",
      "Hospital": "PGIMERChandigarh",
      "Contact": "7087009801",
      "Email": "dhaliwal.navneet@pgimer.edu.in"
    },
    {
      "state": "CHANDIGARH",
      "District": "CHANDIGARH",
      "Hospital": "GovtMultispecialityHospitalSector16Chandigarh",
      "Contact": "7837318507",
      "Email": "gmsh.ms@gmail.com"
    },
    {
      "state": "CHANDIGARH",
      "District": "CHANDIGARH",
      "Hospital": "CivilHospitalSector45",
      "Contact": "9815186028",
      "Email": "ayushmanbharat45@gmail.com"
    },
    {
      "state": "CHANDIGARH",
      "District": "CHANDIGARH",
      "Hospital": "CivilHospitalSector22",
      "Contact": "9914147220",
      "Email": "zone2chc22incharge@gmail.com"
    },
    {
      "state": "CHANDIGARH",
      "District": "CHANDIGARH",
      "Hospital": "CivilHospitalManimajraUTChandigarh",
      "Contact": "9815037088",
      "Email": "civilhospitalmm@gmail.com"
    },
    {
      "state": "CHANDIGARH",
      "District": "CHANDIGARH",
      "Hospital": "GovernmentMedicalCollegeAndHospitalChandigarh",
      "Contact": "9646121551",
      "Email": "hodforensicgmch@gmail.com"
    },
    {
      "state": "CHANDIGARH",
      "District": "CHANDIGARH",
      "Hospital": "EDENCRITICALCAREHOSPITALLTD",
      "Contact": "9814114214",
      "Email": "edenmarketingchd@gmail.com"
    },
    {
      "state": "CHANDIGARH",
      "District": "CHANDIGARH",
      "Hospital": "landmarkhospital",
      "Conatct": "9216870701",
      "Email": "hospitallandmark@gmail.com"
    },
    {
      "state": "CHANDIGARH",
      "District": "CHANDIGARH",
      "Hospital": "SantokhHospital",
      "Contact": "8195900846",
      "Email": "santokhhospitaladmn@gmail.com"
    },
    {
      "state": "CHANDIGARH",
      "District": "CHANDIGARH",
      "Hospital": "Globalhealthcare",
      "Contact": "9815579797",
      "Email": "globalhealthcarechandigarh@gmail.com"
    },
    {
      "state": "CHANDIGARH",
      "District": "CHANDIGARH",
      "Hospital": "DRASHOKSHARMASCORNEACENTRE",
      "Contact": "9855484495",
      "Email": "asharmapgius@yahoo.com"
    },
    {
      "state": "CHANDIGARH",
      "District": "CHANDIGARH",
      "Hospital": "CHDCITYHOSPITAL",
      "Conatct": "9996666997",
      "Email": "gauravjeet.apollo.cch@gmail.com"
    },
    {
      "state": "CHANDIGARH",
      "District": "CHANDIGARH",
      "Hospital": "DASAMKIRATDIALYSISCENTERPVT.LTD.",
      "Conatct": "9872141264",
      "Email": "dkdc.chd@gmail.com"
    },
    {
      "state": "CHANDIGARH",
      "District": "CHANDIGARH",
      "Hospital": "ARVHEALTHCAREPRIVATELTD",
      "Conatct": "8968917981",
      "Email": "arvhealthcare21@gmail.com"
    },
    {
      "state": "CHANDIGARH",
      "District": "CHANDIGARH",
      "Hospital": "BediHospital",
      "Conatct": "9877864797",
      "Email": "insurance.bedihospital@gmail.com"
    },
    {
      "state": "CHANDIGARH",
      "District": "CHANDIGARH",
      "Hospital": "HealingHospitalAndInstituteofParamedicalSciences",
      "Contact": "9316007807",
      "Email": "hhcoordinator34@gmail.com"
    },
    {
      "state": "CHANDIGARH",
      "District": "CHANDIGARH",
      "Hospital": "RAHIcareprivatelimited",
      "Conatct": "9779925382",
      "Email": "haurya.tayal@rahicare.com"
    },
    {
      "state": "CHANDIGARH",
      "District": "CHANDIGARH",
      "Hospital": "GovernmentMedicalCollegeAndHospitalChandigarh",
      "Contact": "9646121551",
      "Email": "hodforensicgmch@gmail.com"
    },
    {
      "state": "CHANDIGARH",
      "District": "CHANDIGARH",
      "Hospital": "AMARSHAKTIEYE&GYNAECLINIC",
      "Conatct": "9878722281",
      "Email": "amarshaktieyecentre@gmail.com"
    },
    {
      "state": "CHANDIGARH",
      "District": "CHANDIGARH",
      "Hospital": "BANSALEYEANDRETINACENTRE",
      "Conatct": "9646121589",
      "Email": "bansalrk@hotmail.com"
    },
    {
      "state": "CHANDIGARH",
      "District": "CHANDIGARH",
      "Hospital": "AKALEYEHOSPITAL",
      "Contact": "7986965860",
      "Email": "akaltpadesk@gmail.com"
    },
    {
      "state": "CHANDIGARH",
      "District": "CHANDIGARH",
      "Hospital": "AKASHDEEPHOSPITAL",
      "Contact": "8591018820",
      "Email": "info.akashdeephospital@gmail.com"
    },
    {
      "state": "CHANDIGARH",
      "District": "CHANDIGARH",
      "Hospital": "BEEENNGENERALHOSPITAL",
      "Contact": "9070325712",
      "Email": "rksharma3594@gmail.co"
    },
    {
      "state": "CHANDIGARH",
      "District": "CHANDIGARH",
      "Hospital": "CARE&CUREMEDICITYHOSPITAL",
      "Contact": "7986939495",
      "Email": "ccmhospital1@gmail.com"
    },
    {
      "state": "CHANDIGARH",
      "District": "CHANDIGARH",
      "Hospital": "DRKOCHARSHOUSEOFSMILES",
      "Contact": "8196819609",
      "Email": "tco.drkochars@gmail.com"
    },
    {
      "state": "CHANDIGARH",
      "District": "CHANDIGARH",
      "Hospital": "DR.ShakeenEyeandDentalHospital",
      "Contact": "9814150026",
      "Email": "himanshu@sightandsmile.com"
    },
    {
      "state": "CHANDIGARH",
      "District": "CHANDIGARH",
      "Hospital": "FLOREMHOSPITAL",
      "Contact": "9815686161",
      "Email": "floremhospital@gmail.com"
    },
    {
      "state": "CHANDIGARH",
      "District": "CHANDIGARH",
      "Hospital": "GREWALEYEINSTITUTE-CHANDIGARH",
      "Contact": "9779188883",
      "Email": "corporate@gei.co.in"
    },
    {
      "state": "CHANDIGARH",
      "District": "CHANDIGARH",
      "Hospital": "SantokhHospital",
      "Contact": "8195900846",
      "Email": "santokhhospitaladmn@gmail.com"
    },
    {
      "state": "CHANDIGARH",
      "District": "CHANDIGARH",
      "Hospital": "GROVEREYELASER&ENTHOSPITAL",
      "Contact": "9216666440",
      "Email": "groverhospital@rediffmail.com"
    },
    {
      "state": "CHANDIGARH",
      "District": "CHANDIGARH",
      "Hospital": "GUMBEREYEANDDENTALCARECENTRE",
      "Contact": "9814030528",
      "Email": "jsgumber@gmail.com"
    },
    {
      "state": "CHANDIGARH",
      "District": "CHANDIGARH",
      "Hospital": "KIDNEYHOSPITAL&LIFELINEMEDICALINSTITUTIONS",
      "Contact": "9872588025",
      "Email": "kidneyhospital@ymail.com"
    },
    {
      "state": "CHANDIGARH",
      "District": "CHANDIGARH",
      "Hospital": "LIFEKAREHOSPITAL",
      "Contact": "8146133388",
      "Email": "lifekarehospital@yahoo.com"
    },
    {
      "state": "CHANDIGARH",
      "District": "CHANDIGARH",
      "Hospital": "MAHARISHIMARKANDESHWARINSTITUTEOFMEDICALSCIEN",
      "Contact": "8607438460",
      "Email": "rahul.ayushmaan@mmumullana.org"
    },
    {
      "state": "CHANDIGARH",
      "District": "CHANDIGARH",
      "Hospital": "MIRCHIASDIAGNOSTIC",
      "Contact": "9855476186",
      "Email": "deepakriyasharma@gmail.com"
    },
    {
      "state": "CHANDIGARH",
      "District": "CHANDIGARH",
      "Hospital": "NAYYARHEARTINSTITUTEANDSUPERSPECIALITYHOSP",
      "Contact": "9814050606",
      "Email": "info.nayyarhospital@gmail.com"
    },
    {
      "state": "CHANDIGARH",
      "District": "CHANDIGARH",
      "Hospital": "NirmaljotEyeHospital",
      "Contact": "8847093251",
      "Email": "nirmaljot99@gmail.com"
    },
    {
      "state": "CHANDIGARH",
      "District": "CHANDIGARH",
      "Hospital": "SHRIMANNSUPERSPECIALITYHOSPITAL",
      "Contact": "9356472166",
      "Email": "tpa@shrimannhospitals.com"
    },
    {
      "state": "CHANDIGARH",
      "District": "CHANDIGARH",
      "Hospital": "SUPERBMRI&CTSCANCENTRE",
      "Contact": "9216870704",
      "Email": "rajindersaini2012@gmail.com"
    },
    {
      "state": "CHANDIGARH",
      "District": "CHANDIGARH",
      "Hospital": "CAREMAXSUPERSPECIALITYHOSPITAL.",
      "Contact": "9877165904",
      "Email": "cashlesscaremaxhospital@gmail.com"
    },
    {
      "state": "CHANDIGARH",
      "District": "CHANDIGARH",
      "Hospital": "MITTALDENTALCLINIC",
      "Contact": "9466337778",
      "Email": "mittaldentalambala@gmail.com"
    },
    {
      "state": "CHANDIGARH",
      "District": "CHANDIGARH",
      "Hospital": "RANJITHOSPITAL",
      "Contact": "8748000004",
      "Eamil": "ranjithospital57@yahoo.in"
    },
    {
      "state": "CHANDIGARH",
      "District": "CHANDIGARH",
      "Hospital": "BBCHeartCare",
      "Contact": "9915015718",
      "Email": "dhadwal1966@gmail.com"
    },
    {
      "state": "CHANDIGARH",
      "District": "CHANDIGARH",
      "Hospital": "CHANDIGARHCLINICALLABORATORIES",
      "Contact": "9814014932",
      "Email": "ccl_chd@yahoo.com"
    },
    {
      "state": "CHANDIGARH",
      "District": "CHANDIGARH",
      "Hospital": "HELIXPATHLABS",
      "Contact": "9915202283",
      "Email": "helixpathlabs@gmail.com"
    },
    {
      "state": "CHANDIGARH",
      "District": "CHANDIGARH",
      "Hospital": "JOSHISUPERSPECILAITYANDMULTISPECIALITYHOSPITAL",
      "Contact": "9417007288",
      "Email": "joshihospital1991@gmail.com"
    },
    {
      "state": "CHANDIGARH",
      "District": "CHANDIGARH",
      "Hospital": "LEELAWATIHOSPITAL",
      "Contact": "9355320376",
      "Email": "leelawatihospital@gmail.com"
    },
    {
      "state": "CHANDIGARH",
      "District": "CHANDIGARH",
      "Hospital": "MEDCARDMULTISPECIALITYHOSPITAL",
      "Contact": "9915199525",
      "Email": "management.medcard@gmail.com"
    },
    {
      "state": "CHANDIGARH",
      "District": "CHANDIGARH",
      "Hospital": "NEUROPSYCHIATRICHOSPITALANDANRCENTREFOROPIAT",
      "Contact": "9780975110",
      "Email": "anrcentre309@gmail.com"
    },
    {
    "state": "CHANDIGARH",
    "District": "CHANDIGARH",
    "Hospital": "PARASHOSPITALSPANCHKULA",
    "Contact": "8130295895",
    "Email": "cghs.pkl@parashospitals.com"
    }
]
